dsa_actionkit/__init__.py
dsa_actionkit/aktemplates.py
dsa_actionkit/moveon_fakeapi.py
dsa_actionkit/settings.py
dsa_actionkit/test.py
dsa_actionkit/contexts/__init__.py
dsa_actionkit/contexts/account_contexts.py
dsa_actionkit/contexts/donation_contexts.py
dsa_actionkit/contexts/event_context_json.py
dsa_actionkit/contexts/event_contexts.py
dsa_actionkit/contexts/event_places.csv
dsa_actionkit/contexts/lib.py
dsa_actionkit/contexts/page_contexts.py
dsa_actionkit/contexts/survey_contexts.py
dsa_actionkit/templates/homepagetest.html
dsa_actionkit/templates/wrapper.html
dsa_actionkit/templatetags/__init__.py
dsa_actionkit/templatetags/actionkit_tags.py
dsa_actionkit/templatetags/ak_universal.py
dsa_actionkit/templatetags/humanize.py
dsa_actionkit/templatetags/smartif.py
dsa_actionkit/templatetags/switchcase.py
dsa_actionkit-0.1.7.dist-info/LICENSE
dsa_actionkit-0.1.7.dist-info/METADATA
dsa_actionkit-0.1.7.dist-info/WHEEL
dsa_actionkit-0.1.7.dist-info/entry_points.txt
dsa_actionkit-0.1.7.dist-info/top_level.txt
dsa_actionkit-0.1.7.dist-info/RECORD
