Metadata-Version: 2.1
Name: dsa-actionkit
Version: 0.1.7
Summary: actionkit-templates allows you to view your ActionKit templates locally testing different configurations for each page type.  It also documents by-code many context variables for each page
Author-email: DSA NTC <ntc@dsacommittees.org>, Schuyler Duveen <opensource@moveon.org>
License: Copyright MoveOn.org written by Schuyler Duveen
Keywords: actionkit
Classifier: Development Status :: 4 - Beta
Classifier: Environment :: Console
Classifier: Intended Audience :: Developers
Classifier: Natural Language :: English
Classifier: Operating System :: OS Independent
Requires-Python: <3.12
License-File: LICENSE
Requires-Dist: django ==3.2.6
Requires-Dist: requests >=2.22.0
Requires-Dist: django-extensions
Requires-Dist: build
Provides-Extra: test
Requires-Dist: selenium >=3.8.0 ; extra == 'test'
Requires-Dist: pyvirtualdisplay ; extra == 'test'
